asext/__init__.py
asext/_version.py
asext/cell.py
asext/struct.py
asext/io/__init__.py
asext/io/readwrite.py
asext-25.12.1.dev1.dist-info/METADATA
asext-25.12.1.dev1.dist-info/WHEEL
asext-25.12.1.dev1.dist-info/licenses/LICENSE.md
asext-25.12.1.dev1.dist-info/RECORD
